{"sequence":[{"name":"snapd","snap-id":"PMrrV4ml8uWuEUDBT8dSGnKUYbevVhc4","revision":"12704"},{"name":"snapd","snap-id":"PMrrV4ml8uWuEUDBT8dSGnKUYbevVhc4","revision":"16292","channel":"latest/stable","title":"snapd","summary":"Daemon and tooling that enable snap packages","description":"Install, configure, refresh and remove snap packages. Snaps are\n'universal' packages that work across many different Linux systems,\nenabling secure distribution of the latest apps and utilities for\ncloud, servers, desktops and the internet of things.\n\nStart with 'snap list' to see installed snaps.\n"}],"current":"16292","migrated-hidden":false,"migrated-exposed-home":false}